etl/__init__.py
etl/etl.py
etl/models.py
etl/functions/__init__.py
etl/functions/ccsv.py
etl/functions/general.py
etl/utils/__init__.py
etl/utils/database.py
etl/utils/exceptions.py
etl/utils/log.py
etl/utils/runtime.py
etl/utils/utils.py
tests/__init__.py
tests/conftest.py
tests/test_logcommit/__init__.py
tests/test_logcommit/test_logcommit.py
generic_etl-0.0.1.dist-info/METADATA
generic_etl-0.0.1.dist-info/WHEEL
generic_etl-0.0.1.dist-info/entry_points.txt
generic_etl-0.0.1.dist-info/top_level.txt
generic_etl-0.0.1.dist-info/RECORD
