Metadata-Version: 2.1
Name: generic-etl
Version: 0.0.1
Author: Christian Decker
Requires-Dist: dynamic-yaml (==1.3.3)
Requires-Dist: greenlet (==1.1.3.post0)
Requires-Dist: numpy (==1.23.4)
Requires-Dist: pandas (==1.5.1)
Requires-Dist: psycopg2-binary (==2.9.4)
Requires-Dist: pyaml (==21.10.1)
Requires-Dist: python-dateutil (==2.8.2)
Requires-Dist: pytz (==2022.5)
Requires-Dist: PyYAML (==6.0)
Requires-Dist: six (==1.16.0)
Requires-Dist: SQLAlchemy (==1.4.42)
Requires-Dist: cx-Oracle (==8.3.0)
